clang_tidier/__init__.py
clang_tidier/colour.py
clang_tidier/main.py
clang_tidier/paths.py
clang_tidier/version.py
clang_tidier/version.txt
clang_tidier-0.11.1.dist-info/licenses/LICENSE.txt
clang_tidier-0.11.1.dist-info/METADATA
clang_tidier-0.11.1.dist-info/WHEEL
clang_tidier-0.11.1.dist-info/entry_points.txt
clang_tidier-0.11.1.dist-info/top_level.txt
clang_tidier-0.11.1.dist-info/zip-safe
clang_tidier-0.11.1.dist-info/RECORD
