Metadata-Version: 2.4
Name: clang-tidier
Version: 0.11.1
Summary: A simple runner for clang-tidy.
Author-email: Mark Gillard <mark.gillard@outlook.com.au>
License: MIT
Project-URL: Source, https://github.com/marzer/clang-tidier
Project-URL: Tracker, https://github.com/marzer/clang-tidier/issues
Project-URL: Funding, https://github.com/sponsors/marzer
Keywords: c++,clang-tidy
Classifier: Development Status :: 3 - Alpha
Classifier: Programming Language :: C
Classifier: Programming Language :: C++
Classifier: Topic :: Software Development
Classifier: Topic :: Software Development :: Testing
Classifier: Topic :: Software Development :: Compilers
Classifier: Topic :: Software Development :: Build Tools
Classifier: Topic :: Software Development :: Bug Tracking
Classifier: Topic :: Utilities
Requires-Python: >=3.8
License-File: LICENSE.txt
Requires-Dist: misk>=0.8.1
Requires-Dist: colorama
Dynamic: license-file
